terminol/__init__.py
terminol/colors.py
terminol-0.1.0.dist-info/LICENSE
terminol-0.1.0.dist-info/METADATA
terminol-0.1.0.dist-info/WHEEL
terminol-0.1.0.dist-info/top_level.txt
terminol-0.1.0.dist-info/RECORD
