Metadata-Version: 2.1
Name: terminol
Version: 0.1.0
Summary: UNIX Terminal utilities so simple you can do it when you're drunk.
Author-email: FyraLabs <contact@fyralabs.com>
License: MIT License
Project-URL: Homepage, https://github.com/FyraLabs/pyterminol
Keywords: tui,cli,color,terminal,input
Classifier: License :: OSI Approved :: MIT License
Classifier: Programming Language :: Python
Classifier: Programming Language :: Python :: 3
Classifier: Topic :: Terminals
Requires-Python: >=3.9
License-File: LICENSE
Provides-Extra: dev
Requires-Dist: black ; extra == 'dev'
Requires-Dist: bumpver ; extra == 'dev'
Requires-Dist: isort ; extra == 'dev'
Requires-Dist: pip-tools ; extra == 'dev'
Requires-Dist: pytest ; extra == 'dev'
